datahub_airflow_plugin/__init__.py
datahub_airflow_plugin/datahub_plugin.py
cdpdev_datahub_airflow_plugin-0.10.5.dist-info/METADATA
cdpdev_datahub_airflow_plugin-0.10.5.dist-info/WHEEL
cdpdev_datahub_airflow_plugin-0.10.5.dist-info/entry_points.txt
cdpdev_datahub_airflow_plugin-0.10.5.dist-info/top_level.txt
cdpdev_datahub_airflow_plugin-0.10.5.dist-info/RECORD
